{
	"Version": 3,
	"FileReferences": {
		"Moc": "Fuwarin.moc3",
		"Textures": [
			"Fuwarin.2048/texture_00.png"
		],
		"Physics": "Fuwarin.physics3.json",
		"DisplayInfo": "Fuwarin.cdi3.json",
		"Expressions": [
			{
				"Name": "Confused.exp3.json",
				"File": "Confused.exp3.json"
			},
			{
				"Name": "Normal.exp3.json",
				"File": "Normal.exp3.json"
			},
			{
				"Name": "Surprised.exp3.json",
				"File": "Surprised.exp3.json"
			},
			{
				"Name": "EyesClosed.exp3.json",
				"File": "EyesClosed.exp3.json"
			}
		]
	},
	"Groups": [
		{
			"Target": "Parameter",
			"Name": "EyeBlink",
			"Ids": []
		}
	],
	"HitAreas": []
}